da_python/__init__.py
da_python/c_lib_wrap.py
da_python/code_version.py
da_python/da_python_api.py
da_python/da_python_main.cp39-win_amd64.pyd
da_python/onnxruntime.dll
da_python/onnxruntime_providers_shared.dll
da_python/opencv_world420.dll
da_python/paddle2onnx.dll
da_python/libs/__init__.py
da_python/serving/__init__.py
da_python/serving/utils.py
da_python-3.1.0.dist-info/METADATA
da_python-3.1.0.dist-info/WHEEL
da_python-3.1.0.dist-info/top_level.txt
da_python-3.1.0.dist-info/RECORD
